limblab/README.md
limblab/__init__.py
limblab/config.py
limblab/constants.py
limblab/limb/-Limb-rec_249.vtk
limblab/limb/Limb-rec_250.vtk
limblab/limb/Limb-rec_251.vtk
limblab/limb/Limb-rec_252.vtk
limblab/limb/Limb-rec_253.vtk
limblab/limb/Limb-rec_254.vtk
limblab/limb/Limb-rec_255.vtk
limblab/limb/Limb-rec_256.vtk
limblab/limb/Limb-rec_257.vtk
limblab/limb/Limb-rec_258.vtk
limblab/limb/Limb-rec_259.vtk
limblab/limb/Limb-rec_260.vtk
limblab/limb/Limb-rec_261.vtk
limblab/limb/Limb-rec_262.vtk
limblab/limb/Limb-rec_263.vtk
limblab/limb/Limb-rec_264.vtk
limblab/limb/Limb-rec_265.vtk
limblab/limb/Limb-rec_266.vtk
limblab/limb/Limb-rec_267.vtk
limblab/limb/Limb-rec_268.vtk
limblab/limb/Limb-rec_269.vtk
limblab/limb/Limb-rec_270.vtk
limblab/limb/Limb-rec_271.vtk
limblab/limb/Limb-rec_272.vtk
limblab/limb/Limb-rec_273.vtk
limblab/limb/Limb-rec_274.vtk
limblab/limb/Limb-rec_275.vtk
limblab/limb/Limb-rec_276.vtk
limblab/limb/Limb-rec_277.vtk
limblab/limb/Limb-rec_278.vtk
limblab/limb/Limb-rec_279.vtk
limblab/limb/Limb-rec_280.vtk
limblab/limb/Limb-rec_281.vtk
limblab/limb/Limb-rec_282.vtk
limblab/limb/Limb-rec_283.vtk
limblab/limb/Limb-rec_284.vtk
limblab/limb/Limb-rec_285.vtk
limblab/limb/Limb-rec_286.vtk
limblab/limb/Limb-rec_287.vtk
limblab/limb/Limb-rec_288.vtk
limblab/limb/Limb-rec_289.vtk
limblab/limb/Limb-rec_290.vtk
limblab/main.py
limblab/pipeline.py
limblab/tools.py
limblab/utils.py
limblab/visualizations.py
limblab-0.4.0.dist-info/METADATA
limblab-0.4.0.dist-info/WHEEL
limblab-0.4.0.dist-info/entry_points.txt
limblab-0.4.0.dist-info/RECORD
