Metadata-Version: 2.3
Name: limblab
Version: 0.4.0
Summary: 
Author: LauAvinyo
Author-email: avinyo.laura@gmail.com
Requires-Python: >=3.10,<4.0
Classifier: Programming Language :: Python :: 3
Classifier: Programming Language :: Python :: 3.10
Classifier: Programming Language :: Python :: 3.11
Classifier: Programming Language :: Python :: 3.12
Classifier: Programming Language :: Python :: 3.13
Provides-Extra: docs
Requires-Dist: click (>=8.2.0,<9.0.0)
Requires-Dist: mkdocs (>=1.5.0,<2.0.0) ; extra == "docs"
Requires-Dist: mkdocs-material (>=9.5.0,<10.0.0) ; extra == "docs"
Requires-Dist: pip-system-certs (>=4.0)
Requires-Dist: pymdown-extensions (>=10.7.0,<11.0.0) ; extra == "docs"
Requires-Dist: requests (>=2.32.3,<3.0.0)
Requires-Dist: scipy (>=1.14.1,<2.0.0)
Requires-Dist: typer[all] (>=0.16.0,<1.0.0)
Requires-Dist: vedo (>=2025,<2026)
